<?xml version="1.0" encoding="UTF-8"?>
<beans xmlns="http://www.springframework.org/schema/beans"
       xmlns:xsi="http://www.w3.org/2001/XMLSchema-instance"
       xmlns:context="http://www.springframework.org/schema/context"
       xmlns:aop="http://www.springframework.org/schema/aop"
       xmlns:tx="http://www.springframework.org/schema/tx"
       xsi:schemaLocation="http://www.springframework.org/schema/beans
       http://www.springframework.org/schema/beans/spring-beans.xsd
       http://www.springframework.org/schema/context
       http://www.springframework.org/schema/context/spring-context.xsd
       http://www.springframework.org/schema/aop
       http://www.springframework.org/schema/aop/spring-aop.xsd
       http://www.springframework.org/schema/tx
       http://www.springframework.org/schema/tx/spring-tx.xsd">
    <!--Spring扫描 除了Controller之外的包注解-->
    <context:component-scan base-package="cn.Liyajun">
        <context:exclude-filter type="annotation" expression="org.springframework.stereotype.Controller"/>
    </context:component-scan>

    <!--读取jdbc.properties-->
    <context:property-placeholder location="classpath:jdbc.properties"/>
    <!-- 配置druid数据源 -->
    <bean name="pooledDataSource" class="com.alibaba.druid.pool.DruidDataSource"
          init-method="init" destroy-method="close">
        <!-- 数据库连接基础信息 -->
        <property name="driverClassName" value="${jdbc.driver}"/>
        <property name="url" value="${jdbc.url}"/>
        <property name="username" value="${jdbc.username}"/>
        <property name="password" value="${jdbc.password}"/>
        <!-- 初始化连接大小 -->
        <property name="initialSize" value="10" />
        <!-- 连接池最大使用连接数量 -->
        <property name="maxActive" value="1500" />
        <!-- 连接池最小空闲 -->
        <property name="minIdle" value="10" />
        <!-- 获取连接最大等待时间 -->
        <property name="maxWait" value="100" />
        <!-- 建议配置为true，不影响性能，并且保证安全性。申请连接的时候检测，如果空闲时间大于timeBetweenEvictionRunsMillis，执行validationQuery检测连接是否有效。 -->
        <property name="testWhileIdle" value="true" />
        <!-- 申请连接时执行validationQuery检测连接是否有效，配置true会降低性能。 -->
        <property name="testOnBorrow" value="false" />
        <!-- 归还连接时执行validationQuery检测连接是否有效，配置true会降低性能 -->
        <property name="testOnReturn" value="false" />

        <!-- 配置间隔多久才进行一次检测，检测需要关闭的空闲连接，单位是毫秒 -->
        <property name="timeBetweenEvictionRunsMillis" value="60000" />
        <!-- 配置一个连接在池中最小生存的时间，单位是毫秒 -->
        <property name="minEvictableIdleTimeMillis" value="25200000" />

        <!-- 对于长时间不使用的连接强制关闭 -->
        <property name="removeAbandoned" value="true" />
        <!-- 关闭超过30分钟的空闲连接，1800秒，也就是30分钟 -->
        <property name="removeAbandonedTimeout" value="1800" />

        <!-- 监控数据库 -->
        <property name="filters" value="stat,wall" />
    </bean>


    <!-- 配置事务管理器 -->
    <bean id="transactionManager" class="org.springframework.jdbc.datasource.DataSourceTransactionManager">
        <property name="dataSource" ref="pooledDataSource" />
    </bean>
    <!--事务管理配置事务操作策略（通知）-->
    <tx:advice id="txAdvice" transaction-manager="transactionManager">
        <tx:attributes>
            <!--查询方法的事务-->
            <tx:method name="query*" read-only="true"/>
            <!--增删改方法的事务-->
            <tx:method name="*" propagation="REQUIRED" isolation="DEFAULT"/>
            <!--如果第一个满足条件,就不会走第二个,所以有顺序问题-->
        </tx:attributes>
    </tx:advice>
    <!--利用AOP切面编程，将事务策略织入到每一个业务层方法中-->
    <aop:config>
        <aop:pointcut id="txPointcut" expression="execution(* cn.Liyajun.Service.Impl.*.*(..))"/>
        <aop:advisor advice-ref="txAdvice" pointcut-ref="txPointcut"/>
    </aop:config>

    <!--配置druid监控spring jdbc -->
    <bean id="druid-stat-interceptor"
          class="com.alibaba.druid.support.spring.stat.DruidStatInterceptor" />

    <bean id="druid-stat-pointcut" class="org.springframework.aop.support.JdkRegexpMethodPointcut"
          scope="prototype">
        <property name="patterns">
            <list>
                <!--需要扫描代码的包-->
                <value>cn.Liyajun.Controller.*</value>
                <value>cn.Liyajun.Service.*</value>
            </list>
        </property>
    </bean>

    <aop:config proxy-target-class="true">
        <aop:advisor advice-ref="druid-stat-interceptor" pointcut-ref="druid-stat-pointcut"/>
    </aop:config>


    <!--监控数据库druid-->
    <bean id="stat-filter" class="com.alibaba.druid.filter.stat.StatFilter">
        <property name="slowSqlMillis" value="3000" />
        <!--记录sql-->
        <property name="logSlowSql" value="true" />
        <!--记录sql的时候可以合并-->
        <property name="mergeSql" value="true" />
    </bean>
    <!--防火墙过滤-->
    <bean id="wall-filter" class="com.alibaba.druid.wall.WallFilter">
        <!--数据库只能是mysql-->
        <property name="dbType" value="mysql" />
    </bean>





    <!-- Mybatis setting配置-->
    <bean id="setting" class="org.apache.ibatis.session.Configuration">
        <property name="mapUnderscoreToCamelCase" value="true"/>
    </bean>
    <!--  Spring 接管sqlSessionFactory  -->
    <bean id="sqlSessionFactory" class="org.mybatis.spring.SqlSessionFactoryBean">
        <property name="dataSource" ref="pooledDataSource"/>
        <property name="mapperLocations" value="classpath:mappers/*.xml"/>
        <property name="typeAliasesPackage" value="cn.Liyajun.pojo"/>
        <property name="configuration" ref="setting"/>
    </bean>


    <!--因为Spring接管整个工程，对整个工程具有扫描权限，mybatis 定位mapper代理接口，
        Spring将dao层的扫描事宜转交给Mybatis
    -->
    <bean class="org.mybatis.spring.mapper.MapperScannerConfigurer">
        <property name="basePackage" value="cn.Liyajun.Dao"/>
        <!--        名称引用  value-->
        <property name="sqlSessionFactoryBeanName" value="sqlSessionFactory"/>
    </bean>


</beans>